[
  {
    "prefill_ttft_ms_mean": 80.2,
    "prefill_ttft_ms_std": 0.21,
    "decode_tok_per_sec_mean": 15.95,
    "decode_tok_per_sec_std": 0.03,
    "prefill_peak_mem_mb_mean": 15373.6,
    "prefill_peak_mem_mb_std": 0.0,
    "prefill_peak_reserved_mb_mean": 15408.0,
    "prefill_peak_reserved_mb_std": 0.0,
    "decode_peak_mem_mb_mean": 15373.0,
    "decode_peak_mem_mb_std": 0.0,
    "decode_peak_reserved_mb_mean": 15408.0,
    "decode_peak_reserved_mb_std": 0.0,
    "prefill_mem_delta_mb_mean": 48.0,
    "prefill_mem_delta_mb_std": 0.0,
    "decode_mem_delta_mb_mean": -15.9,
    "decode_mem_delta_mb_std": 0.0,
    "prefill_kv_cache_mb_mean": 31.88,
    "prefill_kv_cache_mb_std": 0.0,
    "decode_kv_cache_mb_mean": 31.88,
    "decode_kv_cache_mb_std": 0.0,
    "parameter_mb_mean": 15316.51,
    "parameter_mb_std": 0.0,
    "seq_len": 128,
    "model": "meta-llama/Meta-Llama-3.1-8B-Instruct",
    "backend": "flash",
    "precision": "fp16"
  },
  {
    "prefill_ttft_ms_mean": 99.47,
    "prefill_ttft_ms_std": 0.67,
    "decode_tok_per_sec_mean": 15.9,
    "decode_tok_per_sec_std": 0.01,
    "prefill_peak_mem_mb_mean": 15421.3,
    "prefill_peak_mem_mb_std": 0.0,
    "prefill_peak_reserved_mb_mean": 15478.0,
    "prefill_peak_reserved_mb_std": 0.0,
    "decode_peak_mem_mb_mean": 15419.9,
    "decode_peak_mem_mb_std": 0.0,
    "decode_peak_reserved_mb_mean": 15478.0,
    "decode_peak_reserved_mb_std": 0.0,
    "prefill_mem_delta_mb_mean": 94.6,
    "prefill_mem_delta_mb_std": 0.0,
    "decode_mem_delta_mb_mean": -46.5,
    "decode_mem_delta_mb_std": 0.0,
    "prefill_kv_cache_mb_mean": 47.88,
    "prefill_kv_cache_mb_std": 0.0,
    "decode_kv_cache_mb_mean": 47.88,
    "decode_kv_cache_mb_std": 0.0,
    "parameter_mb_mean": 15316.51,
    "parameter_mb_std": 0.0,
    "seq_len": 256,
    "model": "meta-llama/Meta-Llama-3.1-8B-Instruct",
    "backend": "flash",
    "precision": "fp16"
  },
  {
    "prefill_ttft_ms_mean": 175.79,
    "prefill_ttft_ms_std": 1.51,
    "decode_tok_per_sec_mean": 15.83,
    "decode_tok_per_sec_std": 0.02,
    "prefill_peak_mem_mb_mean": 15518.6,
    "prefill_peak_mem_mb_std": 0.0,
    "prefill_peak_reserved_mb_mean": 15610.0,
    "prefill_peak_reserved_mb_std": 0.0,
    "decode_peak_mem_mb_mean": 15519.6,
    "decode_peak_mem_mb_std": 0.0,
    "decode_peak_reserved_mb_mean": 15610.0,
    "decode_peak_reserved_mb_std": 0.0,
    "prefill_mem_delta_mb_mean": 190.0,
    "prefill_mem_delta_mb_std": 0.0,
    "decode_mem_delta_mb_mean": -108.4,
    "decode_mem_delta_mb_std": 0.0,
    "prefill_kv_cache_mb_mean": 79.88,
    "prefill_kv_cache_mb_std": 0.0,
    "decode_kv_cache_mb_mean": 79.88,
    "decode_kv_cache_mb_std": 0.0,
    "parameter_mb_mean": 15316.51,
    "parameter_mb_std": 0.0,
    "seq_len": 512,
    "model": "meta-llama/Meta-Llama-3.1-8B-Instruct",
    "backend": "flash",
    "precision": "fp16"
  },
  {
    "prefill_ttft_ms_mean": 327.84,
    "prefill_ttft_ms_std": 2.45,
    "decode_tok_per_sec_mean": 15.71,
    "decode_tok_per_sec_std": 0.02,
    "prefill_peak_mem_mb_mean": 15711.1,
    "prefill_peak_mem_mb_std": 0.0,
    "prefill_peak_reserved_mb_mean": 15870.0,
    "prefill_peak_reserved_mb_std": 0.0,
    "decode_peak_mem_mb_mean": 15705.3,
    "decode_peak_mem_mb_std": 0.0,
    "decode_peak_reserved_mb_mean": 15870.0,
    "decode_peak_reserved_mb_std": 0.0,
    "prefill_mem_delta_mb_mean": 378.5,
    "prefill_mem_delta_mb_std": 0.0,
    "decode_mem_delta_mb_mean": -233.2,
    "decode_mem_delta_mb_std": 0.0,
    "prefill_kv_cache_mb_mean": 143.88,
    "prefill_kv_cache_mb_std": 0.0,
    "decode_kv_cache_mb_mean": 143.88,
    "decode_kv_cache_mb_std": 0.0,
    "parameter_mb_mean": 15316.51,
    "parameter_mb_std": 0.0,
    "seq_len": 1024,
    "model": "meta-llama/Meta-Llama-3.1-8B-Instruct",
    "backend": "flash",
    "precision": "fp16"
  },
  {
    "prefill_ttft_ms_mean": 674.38,
    "prefill_ttft_ms_std": 2.23,
    "decode_tok_per_sec_mean": 15.43,
    "decode_tok_per_sec_std": 0.01,
    "prefill_peak_mem_mb_mean": 16098.7,
    "prefill_peak_mem_mb_std": 0.0,
    "prefill_peak_reserved_mb_mean": 16422.0,
    "prefill_peak_reserved_mb_std": 0.0,
    "decode_peak_mem_mb_mean": 16086.8,
    "decode_peak_mem_mb_std": 0.0,
    "decode_peak_reserved_mb_mean": 16422.0,
    "decode_peak_reserved_mb_std": 0.0,
    "prefill_mem_delta_mb_mean": 758.0,
    "prefill_mem_delta_mb_std": 0.0,
    "decode_mem_delta_mb_mean": -483.5,
    "decode_mem_delta_mb_std": 0.0,
    "prefill_kv_cache_mb_mean": 271.88,
    "prefill_kv_cache_mb_std": 0.0,
    "decode_kv_cache_mb_mean": 271.88,
    "decode_kv_cache_mb_std": 0.0,
    "parameter_mb_mean": 15316.51,
    "parameter_mb_std": 0.0,
    "seq_len": 2048,
    "model": "meta-llama/Meta-Llama-3.1-8B-Instruct",
    "backend": "flash",
    "precision": "fp16"
  }
]